infi.recipe.buildout_logging-0.1.7-py2.7-nspkg.pth
infi/recipe/buildout_logging/__init__.py
infi/recipe/buildout_logging/__version__.py
infi/recipe/buildout_logging/tests.py
infi.recipe.buildout_logging-0.1.7.dist-info/LICENSE
infi.recipe.buildout_logging-0.1.7.dist-info/METADATA
infi.recipe.buildout_logging-0.1.7.dist-info/WHEEL
infi.recipe.buildout_logging-0.1.7.dist-info/entry_points.txt
infi.recipe.buildout_logging-0.1.7.dist-info/namespace_packages.txt
infi.recipe.buildout_logging-0.1.7.dist-info/top_level.txt
infi.recipe.buildout_logging-0.1.7.dist-info/RECORD
